pipda/__init__.py
pipda/context.py
pipda/expression.py
pipda/function.py
pipda/operator.py
pipda/piping.py
pipda/reference.py
pipda/symbolic.py
pipda/utils.py
pipda/verb.py
pipda-0.13.1.dist-info/LICENSE
pipda-0.13.1.dist-info/METADATA
pipda-0.13.1.dist-info/WHEEL
pipda-0.13.1.dist-info/RECORD
