Metadata-Version: 2.1
Name: pipda
Version: 0.13.1
Summary: A framework for data piping in python
License: MIT
Author: pwwang
Author-email: pwwang@pwwang.com
Requires-Python: >=3.8,<4.0
Classifier: License :: OSI Approved :: MIT License
Classifier: Programming Language :: Python :: 3
Classifier: Programming Language :: Python :: 3.8
Classifier: Programming Language :: Python :: 3.9
Classifier: Programming Language :: Python :: 3.10
Classifier: Programming Language :: Python :: 3.11
Requires-Dist: executing (>=2.0,<3.0)
